[
    {
        "account_name": "Montgomery Ad Account",
        "account_id": "10154131519365667",
        "ad_name": "Default name - Traffic",
        "ad_id": "23843323784470321",
        "adset_name": "18-45",
        "adset_id": "23843323784430321",
        "campaign_name": "Local Support: Monty Job Fair",
        "campaign_id": "23843323784360321",
        "impressions": "70",
        "inline_link_clicks": "0",
        "clicks": "3",
        "cpc": "0.12",
        "ctr": "4.285714",
        "cpm": "5.142857",
        "cpp": "5.538462",
        "spend": "0.36",
        "created_time": "2019-04-22",
        "reach": "65",
        "frequency": "1.076923",
        "date_start": "2019-04-29",
        "date_stop": "2019-05-05",
        "impression_device": "android_smartphone"
    },
    {
        "account_name": "Montgomery Ad Account",
        "account_id": "10154131519365667",
        "ad_name": "Default name - Traffic",
        "ad_id": "23843323784470321",
        "adset_name": "18-45",
        "adset_id": "23843323784430321",
        "campaign_name": "Local Support: Monty Job Fair",
        "campaign_id": "23843323784360321",
        "impressions": "1",
        "inline_link_clicks": "0",
        "clicks": "0",
        "ctr": "0",
        "cpm": "10",
        "cpp": "10",
        "spend": "0.01",
        "created_time": "2019-04-22",
        "reach": "1",
        "frequency": "1",
        "date_start": "2019-04-29",
        "date_stop": "2019-05-05",
        "impression_device": "desktop"
    },
    {
        "account_name": "Montgomery Ad Account",
        "account_id": "10154131519365667",
        "ad_name": "Default name - Traffic",
        "ad_id": "23843323784470321",
        "adset_name": "18-45",
        "adset_id": "23843323784430321",
        "campaign_name": "Local Support: Monty Job Fair",
        "campaign_id": "23843323784360321",
        "impressions": "69",
        "inline_link_clicks": "2",
        "clicks": "4",
        "cpc": "0.0425",
        "ctr": "5.797101",
        "cpm": "2.463768",
        "cpp": "2.698413",
        "spend": "0.17",
        "created_time": "2019-04-22",
        "reach": "63",
        "frequency": "1.095238",
        "date_start": "2019-04-29",
        "date_stop": "2019-05-05",
        "impression_device": "iphone"
    },
    {
        "account_name": "Montgomery Ad Account",
        "account_id": "10154131519365667",
        "ad_name": "ACQ:_FB_Period4-2019_KTSFist-bump>=2visits",
        "ad_id": "23843325013900321",
        "adset_name": "ACQ:_FB_Period4-2019_KTSFist-bump>=2visits",
        "adset_id": "23843325013880321",
        "campaign_name": "ACQ:_FB_Period4-2019_KTSFist-bump>=2visits",
        "campaign_id": "23843325013860321",
        "impressions": "6345",
        "inline_link_clicks": "16",
        "clicks": "29",
        "cpc": "0.79",
        "ctr": "0.457053",
        "cpm": "3.610717",
        "cpp": "9.73237",
        "spend": "22.91",
        "created_time": "2019-04-22",
        "reach": "2354",
        "frequency": "2.695412",
        "date_start": "2019-04-29",
        "date_stop": "2019-05-05",
        "impression_device": "android_smartphone"
    },
    {
        "account_name": "Montgomery Ad Account",
        "account_id": "10154131519365667",
        "ad_name": "ACQ:_FB_Period4-2019_KTSFist-bump>=2visits",
        "ad_id": "23843325013900321",
        "adset_name": "ACQ:_FB_Period4-2019_KTSFist-bump>=2visits",
        "adset_id": "23843325013880321",
        "campaign_name": "ACQ:_FB_Period4-2019_KTSFist-bump>=2visits",
        "campaign_id": "23843325013860321",
        "impressions": "50",
        "inline_link_clicks": "1",
        "clicks": "1",
        "cpc": "0.28",
        "ctr": "2",
        "cpm": "5.6",
        "cpp": "6.666667",
        "spend": "0.28",
        "created_time": "2019-04-22",
        "reach": "42",
        "frequency": "1.190476",
        "date_start": "2019-04-29",
        "date_stop": "2019-05-05",
        "impression_device": "android_tablet"
    },
    {
        "account_name": "Montgomery Ad Account",
        "account_id": "10154131519365667",
        "ad_name": "ACQ:_FB_Period4-2019_KTSFist-bump>=2visits",
        "ad_id": "23843325013900321",
        "adset_name": "ACQ:_FB_Period4-2019_KTSFist-bump>=2visits",
        "adset_id": "23843325013880321",
        "campaign_name": "ACQ:_FB_Period4-2019_KTSFist-bump>=2visits",
        "campaign_id": "23843325013860321",
        "impressions": "740",
        "inline_link_clicks": "0",
        "clicks": "0",
        "ctr": "0",
        "cpm": "9.040541",
        "cpp": "18.379121",
        "spend": "6.69",
        "created_time": "2019-04-22",
        "reach": "364",
        "frequency": "2.032967",
        "date_start": "2019-04-29",
        "date_stop": "2019-05-05",
        "impression_device": "desktop"
    },
    {
        "account_name": "Montgomery Ad Account",
        "account_id": "10154131519365667",
        "ad_name": "ACQ:_FB_Period4-2019_KTSFist-bump>=2visits",
        "ad_id": "23843325013900321",
        "adset_name": "ACQ:_FB_Period4-2019_KTSFist-bump>=2visits",
        "adset_id": "23843325013880321",
        "campaign_name": "ACQ:_FB_Period4-2019_KTSFist-bump>=2visits",
        "campaign_id": "23843325013860321",
        "impressions": "328",
        "inline_link_clicks": "0",
        "clicks": "0",
        "ctr": "0",
        "cpm": "3.689024",
        "cpp": "6.954023",
        "spend": "1.21",
        "created_time": "2019-04-22",
        "reach": "174",
        "frequency": "1.885057",
        "date_start": "2019-04-29",
        "date_stop": "2019-05-05",
        "impression_device": "ipad"
    },
    {
        "account_name": "Montgomery Ad Account",
        "account_id": "10154131519365667",
        "ad_name": "ACQ:_FB_Period4-2019_KTSFist-bump>=2visits",
        "ad_id": "23843325013900321",
        "adset_name": "ACQ:_FB_Period4-2019_KTSFist-bump>=2visits",
        "adset_id": "23843325013880321",
        "campaign_name": "ACQ:_FB_Period4-2019_KTSFist-bump>=2visits",
        "campaign_id": "23843325013860321",
        "impressions": "6946",
        "inline_link_clicks": "8",
        "clicks": "21",
        "cpc": "0.964286",
        "ctr": "0.302332",
        "cpm": "2.915347",
        "cpp": "7.635747",
        "spend": "20.25",
        "created_time": "2019-04-22",
        "reach": "2652",
        "frequency": "2.619155",
        "date_start": "2019-04-29",
        "date_stop": "2019-05-05",
        "impression_device": "iphone"
    },
    {
        "account_name": "Montgomery Ad Account",
        "account_id": "10154131519365667",
        "ad_name": "ACQ:_FB_Period4-2019_KTSFist-bump>=2visits",
        "ad_id": "23843325013900321",
        "adset_name": "ACQ:_FB_Period4-2019_KTSFist-bump>=2visits",
        "adset_id": "23843325013880321",
        "campaign_name": "ACQ:_FB_Period4-2019_KTSFist-bump>=2visits",
        "campaign_id": "23843325013860321",
        "impressions": "4",
        "inline_link_clicks": "0",
        "clicks": "0",
        "ctr": "0",
        "cpm": "2.5",
        "cpp": "5",
        "spend": "0.01",
        "created_time": "2019-04-22",
        "reach": "2",
        "frequency": "2",
        "date_start": "2019-04-29",
        "date_stop": "2019-05-05",
        "impression_device": "ipod"
    },
    {
        "account_name": "Montgomery Ad Account",
        "account_id": "10154131519365667",
        "ad_name": "ACQ:_FB_Period4-2019_KTSFist-bump>=2visits",
        "ad_id": "23843325013900321",
        "adset_name": "ACQ:_FB_Period4-2019_KTSFist-bump>=2visits",
        "adset_id": "23843325013880321",
        "campaign_name": "ACQ:_FB_Period4-2019_KTSFist-bump>=2visits",
        "campaign_id": "23843325013860321",
        "impressions": "38",
        "inline_link_clicks": "0",
        "clicks": "0",
        "ctr": "0",
        "cpm": "7.105263",
        "cpp": "11.25",
        "spend": "0.27",
        "created_time": "2019-04-22",
        "reach": "24",
        "frequency": "1.583333",
        "date_start": "2019-04-29",
        "date_stop": "2019-05-05",
        "impression_device": "other"
    },
    {
        "account_name": "Montgomery Ad Account",
        "account_id": "10154131519365667",
        "ad_name": "CNT_FB_Period4_2019: \"Asiah Thompson: state champion in speech and...\"",
        "ad_id": "23843340131230321",
        "adset_name": "CNT_FB_Period4_2019  \"Asiah Thompson: state champion in speech and...\"",
        "adset_id": "23843340131180321",
        "campaign_name": "CNT_FB_Period4_2019: \"Asiah Thompson: state champion in speech and...\"",
        "campaign_id": "23843340131160321",
        "impressions": "1150",
        "inline_link_clicks": "11",
        "clicks": "47",
        "cpc": "0.086383",
        "ctr": "4.086957",
        "cpm": "3.530435",
        "cpp": "4.737456",
        "spend": "4.06",
        "created_time": "2019-04-29",
        "reach": "857",
        "frequency": "1.34189",
        "date_start": "2019-04-29",
        "date_stop": "2019-05-05",
        "impression_device": "android_smartphone"
    },
    {
        "account_name": "Montgomery Ad Account",
        "account_id": "10154131519365667",
        "ad_name": "CNT_FB_Period4_2019: \"Asiah Thompson: state champion in speech and...\"",
        "ad_id": "23843340131230321",
        "adset_name": "CNT_FB_Period4_2019  \"Asiah Thompson: state champion in speech and...\"",
        "adset_id": "23843340131180321",
        "campaign_name": "CNT_FB_Period4_2019: \"Asiah Thompson: state champion in speech and...\"",
        "campaign_id": "23843340131160321",
        "impressions": "1",
        "inline_link_clicks": "0",
        "clicks": "0",
        "ctr": "0",
        "cpm": "10",
        "cpp": "10",
        "spend": "0.01",
        "created_time": "2019-04-29",
        "reach": "1",
        "frequency": "1",
        "date_start": "2019-04-29",
        "date_stop": "2019-05-05",
        "impression_device": "android_tablet"
    },
    {
        "account_name": "Montgomery Ad Account",
        "account_id": "10154131519365667",
        "ad_name": "CNT_FB_Period4_2019: \"Asiah Thompson: state champion in speech and...\"",
        "ad_id": "23843340131230321",
        "adset_name": "CNT_FB_Period4_2019  \"Asiah Thompson: state champion in speech and...\"",
        "adset_id": "23843340131180321",
        "campaign_name": "CNT_FB_Period4_2019: \"Asiah Thompson: state champion in speech and...\"",
        "campaign_id": "23843340131160321",
        "impressions": "20",
        "inline_link_clicks": "0",
        "clicks": "0",
        "ctr": "0",
        "cpm": "4.5",
        "cpp": "5.625",
        "spend": "0.09",
        "created_time": "2019-04-29",
        "reach": "16",
        "frequency": "1.25",
        "date_start": "2019-04-29",
        "date_stop": "2019-05-05",
        "impression_device": "desktop"
    },
    {
        "account_name": "Montgomery Ad Account",
        "account_id": "10154131519365667",
        "ad_name": "CNT_FB_Period4_2019: \"Asiah Thompson: state champion in speech and...\"",
        "ad_id": "23843340131230321",
        "adset_name": "CNT_FB_Period4_2019  \"Asiah Thompson: state champion in speech and...\"",
        "adset_id": "23843340131180321",
        "campaign_name": "CNT_FB_Period4_2019: \"Asiah Thompson: state champion in speech and...\"",
        "campaign_id": "23843340131160321",
        "impressions": "7",
        "inline_link_clicks": "0",
        "clicks": "0",
        "ctr": "0",
        "cpm": "4.285714",
        "cpp": "4.285714",
        "spend": "0.03",
        "created_time": "2019-04-29",
        "reach": "7",
        "frequency": "1",
        "date_start": "2019-04-29",
        "date_stop": "2019-05-05",
        "impression_device": "ipad"
    },
    {
        "account_name": "Montgomery Ad Account",
        "account_id": "10154131519365667",
        "ad_name": "CNT_FB_Period4_2019: \"Asiah Thompson: state champion in speech and...\"",
        "ad_id": "23843340131230321",
        "adset_name": "CNT_FB_Period4_2019  \"Asiah Thompson: state champion in speech and...\"",
        "adset_id": "23843340131180321",
        "campaign_name": "CNT_FB_Period4_2019: \"Asiah Thompson: state champion in speech and...\"",
        "campaign_id": "23843340131160321",
        "impressions": "1549",
        "inline_link_clicks": "10",
        "clicks": "51",
        "cpc": "0.113922",
        "ctr": "3.292447",
        "cpm": "3.750807",
        "cpp": "5.310786",
        "spend": "5.81",
        "created_time": "2019-04-29",
        "reach": "1094",
        "frequency": "1.415905",
        "date_start": "2019-04-29",
        "date_stop": "2019-05-05",
        "impression_device": "iphone"
    },
    {
        "account_name": "Montgomery Ad Account",
        "account_id": "10154131519365667",
        "ad_name": "CNT_FB_Period4_2019: \"Asiah Thompson: state champion in speech and...\"",
        "ad_id": "23843340131230321",
        "adset_name": "CNT_FB_Period4_2019  \"Asiah Thompson: state champion in speech and...\"",
        "adset_id": "23843340131180321",
        "campaign_name": "CNT_FB_Period4_2019: \"Asiah Thompson: state champion in speech and...\"",
        "campaign_id": "23843340131160321",
        "impressions": "3",
        "inline_link_clicks": "0",
        "clicks": "0",
        "ctr": "0",
        "cpm": "0",
        "cpp": "0",
        "spend": "0",
        "created_time": "2019-04-29",
        "reach": "3",
        "frequency": "1",
        "date_start": "2019-04-29",
        "date_stop": "2019-05-05",
        "impression_device": "other"
    },
    {
        "account_name": "Montgomery Ad Account",
        "account_id": "10154131519365667",
        "ad_name": "CNT_FB_Period4_2019 \"The Alabama Senate issued a resolution this week...\"",
        "ad_id": "23843340132870321",
        "adset_name": "CNT_FB_Period4_2019: \"The Alabama Senate issued a resolution this week...\"",
        "adset_id": "23843340132850321",
        "campaign_name": "CNT_FB_Period4_2019 \"The Alabama Senate issued a resolution this week...\"",
        "campaign_id": "23843340132780321",
        "impressions": "233",
        "inline_link_clicks": "4",
        "clicks": "9",
        "cpc": "0.054444",
        "ctr": "3.862661",
        "cpm": "2.103004",
        "cpp": "2.227273",
        "spend": "0.49",
        "created_time": "2019-04-29",
        "reach": "220",
        "frequency": "1.059091",
        "date_start": "2019-04-29",
        "date_stop": "2019-05-05",
        "impression_device": "android_smartphone"
    },
    {
        "account_name": "Montgomery Ad Account",
        "account_id": "10154131519365667",
        "ad_name": "CNT_FB_Period4_2019 \"The Alabama Senate issued a resolution this week...\"",
        "ad_id": "23843340132870321",
        "adset_name": "CNT_FB_Period4_2019: \"The Alabama Senate issued a resolution this week...\"",
        "adset_id": "23843340132850321",
        "campaign_name": "CNT_FB_Period4_2019 \"The Alabama Senate issued a resolution this week...\"",
        "campaign_id": "23843340132780321",
        "impressions": "2",
        "inline_link_clicks": "0",
        "clicks": "0",
        "ctr": "0",
        "cpm": "5",
        "cpp": "5",
        "spend": "0.01",
        "created_time": "2019-04-29",
        "reach": "2",
        "frequency": "1",
        "date_start": "2019-04-29",
        "date_stop": "2019-05-05",
        "impression_device": "desktop"
    },
    {
        "account_name": "Montgomery Ad Account",
        "account_id": "10154131519365667",
        "ad_name": "CNT_FB_Period4_2019 \"The Alabama Senate issued a resolution this week...\"",
        "ad_id": "23843340132870321",
        "adset_name": "CNT_FB_Period4_2019: \"The Alabama Senate issued a resolution this week...\"",
        "adset_id": "23843340132850321",
        "campaign_name": "CNT_FB_Period4_2019 \"The Alabama Senate issued a resolution this week...\"",
        "campaign_id": "23843340132780321",
        "impressions": "5",
        "inline_link_clicks": "0",
        "clicks": "0",
        "ctr": "0",
        "cpm": "2",
        "cpp": "2",
        "spend": "0.01",
        "created_time": "2019-04-29",
        "reach": "5",
        "frequency": "1",
        "date_start": "2019-04-29",
        "date_stop": "2019-05-05",
        "impression_device": "ipad"
    },
    {
        "account_name": "Montgomery Ad Account",
        "account_id": "10154131519365667",
        "ad_name": "CNT_FB_Period4_2019 \"The Alabama Senate issued a resolution this week...\"",
        "ad_id": "23843340132870321",
        "adset_name": "CNT_FB_Period4_2019: \"The Alabama Senate issued a resolution this week...\"",
        "adset_id": "23843340132850321",
        "campaign_name": "CNT_FB_Period4_2019 \"The Alabama Senate issued a resolution this week...\"",
        "campaign_id": "23843340132780321",
        "impressions": "532",
        "inline_link_clicks": "2",
        "clicks": "12",
        "cpc": "0.123333",
        "ctr": "2.255639",
        "cpm": "2.781955",
        "cpp": "3.142251",
        "spend": "1.48",
        "created_time": "2019-04-29",
        "reach": "471",
        "frequency": "1.129512",
        "date_start": "2019-04-29",
        "date_stop": "2019-05-05",
        "impression_device": "iphone"
    },
    {
        "account_name": "Montgomery Ad Account",
        "account_id": "10154131519365667",
        "ad_name": "CNT_FB_Period4_2019 \"The Alabama Senate issued a resolution this week...\"",
        "ad_id": "23843340132870321",
        "adset_name": "CNT_FB_Period4_2019: \"The Alabama Senate issued a resolution this week...\"",
        "adset_id": "23843340132850321",
        "campaign_name": "CNT_FB_Period4_2019 \"The Alabama Senate issued a resolution this week...\"",
        "campaign_id": "23843340132780321",
        "impressions": "1",
        "inline_link_clicks": "0",
        "clicks": "0",
        "ctr": "0",
        "cpm": "0",
        "cpp": "0",
        "spend": "0",
        "created_time": "2019-04-29",
        "reach": "1",
        "frequency": "1",
        "date_start": "2019-04-29",
        "date_stop": "2019-05-05",
        "impression_device": "ipod"
    },
    {
        "account_name": "Montgomery Ad Account",
        "account_id": "10154131519365667",
        "ad_name": "CNT_FB_Period4_2019 \"For much of Nick Saban's tenure, Alabama has...\"",
        "ad_id": "23843340134980321",
        "adset_name": "CNT_FB_Period4_2019 \"For much of Nick Saban's tenure, Alabama has...\"",
        "adset_id": "23843340134960321",
        "campaign_name": "CNT_FB_Period4_2019: \"For much of Nick Saban's tenure, Alabama has...\"",
        "campaign_id": "23843340134910321",
        "impressions": "1091",
        "inline_link_clicks": "61",
        "clicks": "112",
        "cpc": "0.042589",
        "ctr": "10.265811",
        "cpm": "4.372136",
        "cpp": "5.156757",
        "spend": "4.77",
        "created_time": "2019-04-29",
        "reach": "925",
        "frequency": "1.179459",
        "date_start": "2019-04-29",
        "date_stop": "2019-05-05",
        "impression_device": "android_smartphone"
    },
    {
        "account_name": "Montgomery Ad Account",
        "account_id": "10154131519365667",
        "ad_name": "CNT_FB_Period4_2019 \"For much of Nick Saban's tenure, Alabama has...\"",
        "ad_id": "23843340134980321",
        "adset_name": "CNT_FB_Period4_2019 \"For much of Nick Saban's tenure, Alabama has...\"",
        "adset_id": "23843340134960321",
        "campaign_name": "CNT_FB_Period4_2019: \"For much of Nick Saban's tenure, Alabama has...\"",
        "campaign_id": "23843340134910321",
        "impressions": "8",
        "inline_link_clicks": "0",
        "clicks": "2",
        "cpc": "0.03",
        "ctr": "25",
        "cpm": "7.5",
        "cpp": "7.5",
        "spend": "0.06",
        "created_time": "2019-04-29",
        "reach": "8",
        "frequency": "1",
        "date_start": "2019-04-29",
        "date_stop": "2019-05-05",
        "impression_device": "android_tablet"
    },
    {
        "account_name": "Montgomery Ad Account",
        "account_id": "10154131519365667",
        "ad_name": "CNT_FB_Period4_2019 \"For much of Nick Saban's tenure, Alabama has...\"",
        "ad_id": "23843340134980321",
        "adset_name": "CNT_FB_Period4_2019 \"For much of Nick Saban's tenure, Alabama has...\"",
        "adset_id": "23843340134960321",
        "campaign_name": "CNT_FB_Period4_2019: \"For much of Nick Saban's tenure, Alabama has...\"",
        "campaign_id": "23843340134910321",
        "impressions": "30",
        "inline_link_clicks": "1",
        "clicks": "3",
        "cpc": "0.043333",
        "ctr": "10",
        "cpm": "4.333333",
        "cpp": "5",
        "spend": "0.13",
        "created_time": "2019-04-29",
        "reach": "26",
        "frequency": "1.153846",
        "date_start": "2019-04-29",
        "date_stop": "2019-05-05",
        "impression_device": "ipad"
    },
    {
        "account_name": "Montgomery Ad Account",
        "account_id": "10154131519365667",
        "ad_name": "CNT_FB_Period4_2019 \"For much of Nick Saban's tenure, Alabama has...\"",
        "ad_id": "23843340134980321",
        "adset_name": "CNT_FB_Period4_2019 \"For much of Nick Saban's tenure, Alabama has...\"",
        "adset_id": "23843340134960321",
        "campaign_name": "CNT_FB_Period4_2019: \"For much of Nick Saban's tenure, Alabama has...\"",
        "campaign_id": "23843340134910321",
        "impressions": "1483",
        "inline_link_clicks": "64",
        "clicks": "101",
        "cpc": "0.049802",
        "ctr": "6.810519",
        "cpm": "3.391773",
        "cpp": "4.184692",
        "spend": "5.03",
        "created_time": "2019-04-29",
        "reach": "1202",
        "frequency": "1.233777",
        "date_start": "2019-04-29",
        "date_stop": "2019-05-05",
        "impression_device": "iphone"
    }
]